power_grid_model_io_native/__init__.py
power_grid_model_io_native/_core/__init__.py
power_grid_model_io_native/_core/error_handling.py
power_grid_model_io_native/_core/power_grid_model_io_core.py
power_grid_model_io_native/_core/_power_grid_model_io_core.so
power_grid_model_io_native/_core/pgm_vnf_converter.py
power_grid_model_io_native-0.1.13.dist-info/RECORD
power_grid_model_io_native-0.1.13.dist-info/LICENSE
power_grid_model_io_native-0.1.13.dist-info/WHEEL
power_grid_model_io_native-0.1.13.dist-info/top_level.txt
power_grid_model_io_native-0.1.13.dist-info/METADATA
