Metadata-Version: 2.2
Name: power-grid-model-io-native
Version: 0.1.13
Summary: Power Grid Model Input/Output with native support
Author-email: Contributors to the Power Grid Model project <powergridmodel@lfenergy.org>
License: MPL-2.0
Project-URL: Home-page, https://lfenergy.org/projects/power-grid-model-io-native/
Project-URL: GitHub, https://github.com/PowerGridModel/power-grid-model-io-native
Project-URL: Documentation, https://power-grid-model-io-native.readthedocs.io/en/stable/
Project-URL: Mailing-list, https://lists.lfenergy.org/g/powergridmodel
Project-URL: Discussion, https://github.com/orgs/PowerGridModel/discussions
Classifier: Programming Language :: Python :: 3
Classifier: Programming Language :: Python :: Implementation :: CPython
Classifier: Programming Language :: C++
Classifier: Development Status :: 2 - Pre-Alpha
Classifier: Intended Audience :: Developers
Classifier: Intended Audience :: Science/Research
Classifier: License :: OSI Approved :: Mozilla Public License 2.0 (MPL 2.0)
Classifier: Operating System :: Microsoft :: Windows
Classifier: Operating System :: POSIX :: Linux
Classifier: Operating System :: MacOS
Classifier: Topic :: Scientific/Engineering :: Physics
Requires-Python: >=3.10
License-File: LICENSE
Requires-Dist: numpy>=1.21.0
Requires-Dist: power-grid-model>=1.8
Provides-Extra: dev
Requires-Dist: msgpack; extra == "dev"
Requires-Dist: pre-commit; extra == "dev"
Requires-Dist: pylint; extra == "dev"
Requires-Dist: pytest; extra == "dev"
Requires-Dist: pytest-cov; extra == "dev"
